Metadata-Version: 1.1
Name: django-websocket-redis
Version: 0.5.1
Summary: Websocket support for Django using Redis as datastore
Home-page: https://github.com/jrief/django-websocket-redis
Author: Jacob Rief
Author-email: jacob.rief@gmail.com
License: MIT
Keywords: django,websocket,redis
Platform: OS Independent
Classifier: Environment :: Web Environment
Classifier: Framework :: Django
Classifier: Framework :: Django :: 1.5
Classifier: Framework :: Django :: 1.6
Classifier: Framework :: Django :: 1.7
Classifier: Framework :: Django :: 1.8
Classifier: Intended Audience :: Developers
Classifier: License :: OSI Approved :: MIT License
Classifier: Operating System :: OS Independent
Classifier: Programming Language :: Python
Classifier: Topic :: Software Development :: Libraries :: Python Modules
Classifier: Development Status :: 4 - Beta
Classifier: Programming Language :: Python :: 2.7
Classifier: Programming Language :: Python :: 3.3
Classifier: Programming Language :: Python :: 3.4
